LICENSE
README.md
setup.py
tap_heap/__init__.py
tap_heap/discover.py
tap_heap/manifest.py
tap_heap/s3.py
tap_heap/schema.py
tap_heap/sync.py
tap_heap.egg-info/PKG-INFO
tap_heap.egg-info/SOURCES.txt
tap_heap.egg-info/dependency_links.txt
tap_heap.egg-info/entry_points.txt
tap_heap.egg-info/requires.txt
tap_heap.egg-info/top_level.txt