Metadata-Version: 2.4
Name: tap-heap
Version: 1.4.0
Summary: Singer.io tap for extracting Heap data from Avro files in S3
Home-page: https://singer.io
Author: Stitch
Classifier: Programming Language :: Python :: 3 :: Only
License-File: LICENSE
Requires-Dist: boto3==1.39.9
Requires-Dist: singer-encodings==0.1.3
Requires-Dist: singer-python==6.1.1
Requires-Dist: python-snappy==0.7.3
Requires-Dist: fastavro==1.11.1
Provides-Extra: dev
Requires-Dist: ipdb; extra == "dev"
Requires-Dist: pylint; extra == "dev"
Requires-Dist: pytest; extra == "dev"
Dynamic: author
Dynamic: classifier
Dynamic: home-page
Dynamic: license-file
Dynamic: provides-extra
Dynamic: requires-dist
Dynamic: summary
